src/__init__.py
src/__main__.py
src/core.py
src/deck.py
src/text_formatter.py
tarot_reader-0.0.4.dist-info/licenses/LICENSE
tarot_reader-0.0.4.dist-info/METADATA
tarot_reader-0.0.4.dist-info/WHEEL
tarot_reader-0.0.4.dist-info/entry_points.txt
tarot_reader-0.0.4.dist-info/top_level.txt
tarot_reader-0.0.4.dist-info/RECORD
