Metadata-Version: 2.4
Name: tarot-reader
Version: 0.0.4
Summary: A lightweight tarot reading package that doubles as a powerful random content generator with personal seed support
Author-email: zafrem <zafrem@gmail.com>
License: MIT License
Project-URL: Homepage, https://github.com/zafrem/tarot-reader
Project-URL: Bug Reports, https://github.com/zafrem/tarot-reader/issues
Project-URL: Source, https://github.com/zafrem/tarot-reader
Keywords: tarot,cards,random,generator,llm,content,seed,entertainment
Classifier: Development Status :: 3 - Alpha
Classifier: Intended Audience :: Developers
Classifier: License :: OSI Approved :: MIT License
Classifier: Operating System :: OS Independent
Classifier: Programming Language :: Python :: 3
Classifier: Programming Language :: Python :: 3.8
Classifier: Programming Language :: Python :: 3.9
Classifier: Programming Language :: Python :: 3.10
Classifier: Programming Language :: Python :: 3.11
Classifier: Programming Language :: Python :: 3.12
Classifier: Topic :: Games/Entertainment
Classifier: Topic :: Software Development :: Libraries :: Python Modules
Requires-Python: >=3.8
License-File: LICENSE
Provides-Extra: dev
Requires-Dist: ruff>=0.1.0; extra == "dev"
Requires-Dist: black>=23.0.0; extra == "dev"
Requires-Dist: mypy>=1.0.0; extra == "dev"
Requires-Dist: pytest>=7.0.0; extra == "dev"
Requires-Dist: pytest-cov>=4.0.0; extra == "dev"
Provides-Extra: test
Requires-Dist: pytest>=7.0.0; extra == "test"
Requires-Dist: pytest-cov>=4.0.0; extra == "test"
Dynamic: license-file
